fds/__init__.py
fds/sdk/__init__.py
fds/sdk/StandardDatafeed/__init__.py
fds/sdk/StandardDatafeed/api_client.py
fds/sdk/StandardDatafeed/configuration.py
fds/sdk/StandardDatafeed/exceptions.py
fds/sdk/StandardDatafeed/model_utils.py
fds/sdk/StandardDatafeed/rest.py
fds/sdk/StandardDatafeed/api/__init__.py
fds/sdk/StandardDatafeed/api/schema_api.py
fds/sdk/StandardDatafeed/api/sdf_and_qfl_content_library_api.py
fds/sdk/StandardDatafeed/apis/__init__.py
fds/sdk/StandardDatafeed/model/__init__.py
fds/sdk/StandardDatafeed/model/error_example.py
fds/sdk/StandardDatafeed/model/error_response.py
fds/sdk/StandardDatafeed/model/historical_file.py
fds/sdk/StandardDatafeed/model/historical_file_object.py
fds/sdk/StandardDatafeed/model/historical_file_object_object.py
fds/sdk/StandardDatafeed/model/list_file.py
fds/sdk/StandardDatafeed/model/list_file_object.py
fds/sdk/StandardDatafeed/model/list_file_object_object.py
fds/sdk/StandardDatafeed/model/list_schema.py
fds/sdk/StandardDatafeed/model/list_schema_object.py
fds/sdk/StandardDatafeed/model/meta.py
fds/sdk/StandardDatafeed/model/pagination.py
fds/sdk/StandardDatafeed/model/schema_detail.py
fds/sdk/StandardDatafeed/model/schema_detail_object.py
fds/sdk/StandardDatafeed/models/__init__.py
fds.sdk.StandardDatafeed-1.0.3.dist-info/LICENSE
fds.sdk.StandardDatafeed-1.0.3.dist-info/METADATA
fds.sdk.StandardDatafeed-1.0.3.dist-info/WHEEL
fds.sdk.StandardDatafeed-1.0.3.dist-info/top_level.txt
fds.sdk.StandardDatafeed-1.0.3.dist-info/RECORD
